opensees_copilot/__init__.py
opensees_copilot/cli.py
opensees_copilot-0.0.1.dist-info/METADATA
opensees_copilot-0.0.1.dist-info/WHEEL
opensees_copilot-0.0.1.dist-info/entry_points.txt
opensees_copilot-0.0.1.dist-info/licenses/LICENSE
opensees_copilot-0.0.1.dist-info/RECORD
