Metadata-Version: 2.4
Name: opensees-copilot
Version: 0.0.1
Summary: Scaffolding & CLI hooks for an upcoming OpenSees agent — placeholder release.
Project-URL: Homepage, https://github.com/mohsen-azimi/opensees-copilot
Project-URL: Issues, https://github.com/mohsen-azimi/opensees-copilot/issues
Author: Mohsen Azimi
License: 
License-File: LICENSE
Keywords: OpenSees,OpenSeesPy,agents,copilot,structural-engineering
Classifier: Development Status :: 2 - Pre-Alpha
Classifier: Intended Audience :: Science/Research
Classifier: License :: OSI Approved :: MIT License
Classifier: Programming Language :: Python :: 3
Classifier: Programming Language :: Python :: 3 :: Only
Classifier: Programming Language :: Python :: 3.9
Classifier: Programming Language :: Python :: 3.10
Classifier: Programming Language :: Python :: 3.11
Classifier: Programming Language :: Python :: 3.12
Classifier: Topic :: Scientific/Engineering
Requires-Python: >=3.9
